EOS/Switch.py
EOS/__init__.py
EOS/chips.py
EOS/models.py
EOS/playground.py
EOS/switch_helpers.py
AristaSwitchClient-0.2.2.dist-info/METADATA
AristaSwitchClient-0.2.2.dist-info/WHEEL
AristaSwitchClient-0.2.2.dist-info/top_level.txt
AristaSwitchClient-0.2.2.dist-info/RECORD
