Metadata-Version: 2.1
Name: AristaSwitchClient
Version: 0.2.2
Summary: A quick small library to create quick custom scripts for Arista Switches
Home-page: https://github.com/jrecchia1029/Arista-Switch-Client
Author: Joe Recchia
Author-email: joerecchia@arista.com
License: UNKNOWN
Platform: UNKNOWN
Classifier: Programming Language :: Python :: 3
Classifier: License :: OSI Approved :: MIT License
Classifier: Operating System :: OS Independent
